eznet_torch/__init__.py
eznet_torch/test.py
eznet_torch/utils.py
eznet_torch/models/__init__.py
eznet_torch/models/ann.py
eznet_torch/models/conv_block.py
eznet_torch/models/conv_network.py
eznet_torch/models/dense_block.py
eznet_torch/models/language_model.py
eznet_torch/models/pytorch_smart_module.py
eznet_torch/models/recurrent_network.py
eznet_torch-0.0.1.dist-info/LICENSE.txt
eznet_torch-0.0.1.dist-info/METADATA
eznet_torch-0.0.1.dist-info/WHEEL
eznet_torch-0.0.1.dist-info/top_level.txt
eznet_torch-0.0.1.dist-info/RECORD
