Metadata-Version: 2.1
Name: eznet-torch
Version: 0.0.1
Summary: Easily build PyTorch models: utils for training/testing, built-in ANN, CNN, RNN models, modular Dense and Convolutional blocks, etc.
Home-page: https://github.com/pniaz20/eznet_torch
Author: Pouya P. Niaz
Author-email: <pniaz20@ku.edu.tr>
License: MIT
Keywords: torch,pytorch,deep learning,neural network
Classifier: Development Status :: 3 - Alpha
Classifier: Intended Audience :: End Users/Desktop
Classifier: Intended Audience :: Education
Classifier: Intended Audience :: Science/Research
Classifier: License :: OSI Approved :: MIT License
Classifier: Programming Language :: Python :: 3
Classifier: Operating System :: OS Independent
Classifier: Topic :: Utilities
Classifier: Topic :: Education
Classifier: Topic :: Scientific/Engineering
Classifier: Topic :: Scientific/Engineering :: Artificial Intelligence
Requires-Python: >=3.7, <4
License-File: LICENSE.txt
Requires-Dist: numpy
Requires-Dist: tqdm
Requires-Dist: scikit-learn
Requires-Dist: torch
